{"title":"Streaming ETL Pipeline with Confluent","description":"","widgets":[{"id":0,"definition":{"type":"image","url":"/static/images/saas_logos/bot/postgres.png","sizing":"zoom"},"layout":{"x":1,"y":1,"width":20,"height":11}},{"id":1,"definition":{"type":"image","url":"/static/images/saas_logos/bot/mongodb.png","sizing":"zoom"},"layout":{"x":1,"y":44,"width":19,"height":11}},{"id":2,"definition":{"type":"timeseries","requests":[{"q":"sum:postgresql.rows_fetched{*}, sum:postgresql.rows_inserted{*}","metadata":[{"expression":"sum:postgresql.rows_fetched{*}","alias_name":"Postgres Rows Returned"},{"expression":"sum:postgresql.rows_inserted{*}","alias_name":"Postgres Rows Inserted"}],"display_type":"area","style":{"palette":"cool","line_type":"solid","line_width":"normal"}}],"custom_links":[],"yaxis":{"label":"","scale":"linear","min":"auto","max":"auto","include_zero":true},"title":"Rows Inserted / Fetched per Second","title_size":"16","title_align":"left","show_legend":false,"legend_size":"0"},"layout":{"x":1,"y":28,"width":41,"height":15}},{"id":3,"definition":{"type":"image","url":"/static/images/saas_logos/bot/confluent_platform@2x.png","sizing":"zoom"},"layout":{"x":43,"y":1,"width":19,"height":11}},{"id":4,"definition":{"type":"check_status","title":"Postgres Hosts","title_size":"16","title_align":"center","check":"postgres.can_connect","grouping":"cluster","group":"db:postgres,server:localhost,port:5432,server:localhost,host:i-0bccff6999c3c9509","group_by":[],"tags":["*"]},"layout":{"x":22,"y":1,"width":20,"height":11}},{"id":5,"definition":{"type":"check_status","title":"MongoDB Hosts","title_size":"16","title_align":"center","check":"mongodb.can_connect","grouping":"cluster","group":"db:logistics,server:127.0.0.1,port:27017,host:i-0bccff6999c3c9509","group_by":[],"tags":["*"]},"layout":{"x":21,"y":44,"width":21,"height":11}},{"id":6,"definition":{"type":"check_status","title":"Confluent Hosts","title_size":"16","title_align":"center","check":"confluent.can_connect","grouping":"cluster","group":"db:postgres,server:localhost,port:5432,server:localhost,host:i-0bccff6999c3c9509","group_by":[],"tags":["*"]},"layout":{"x":63,"y":1,"width":21,"height":11}},{"id":7,"definition":{"type":"timeseries","requests":[{"q":"sum:mongodb.opcounters.getmoreps{*}, sum:mongodb.opcounters.queryps{*}, sum:mongodb.opcounters.insertps{*}","display_type":"area","style":{"palette":"green","line_type":"solid","line_width":"normal"}}],"custom_links":[],"yaxis":{"label":"","scale":"linear","min":"auto","max":"auto","include_zero":true},"title":"Read / Insert Requests per Second","title_size":"16","title_align":"left","show_legend":false,"legend_size":"0"},"layout":{"x":1,"y":71,"width":41,"height":15}},{"id":8,"definition":{"type":"timeseries","requests":[{"q":"sum:postgresql.connections{*}","display_type":"bars","style":{"palette":"cool","line_type":"solid","line_width":"normal"}}],"custom_links":[],"yaxis":{"label":"","scale":"linear","min":"auto","max":"auto","include_zero":true},"title":"Connections","title_size":"16","title_align":"left","show_legend":false,"legend_size":"0"},"layout":{"x":1,"y":13,"width":41,"height":15}},{"id":9,"definition":{"type":"timeseries","requests":[{"q":"sum:mongodb.connections.current{*}","display_type":"area","style":{"palette":"green","line_type":"solid","line_width":"normal"}}],"custom_links":[],"yaxis":{"label":"","scale":"linear","min":"auto","max":"auto","include_zero":true},"title":"Connections","title_size":"16","title_align":"left","show_legend":false,"legend_size":"0"},"layout":{"x":1,"y":56,"width":41,"height":15}},{"id":10,"definition":{"type":"note","content":"Kafka Connect","background_color":"blue","font_size":"18","text_align":"center","show_tick":true,"tick_pos":"50%","tick_edge":"bottom"},"layout":{"x":43,"y":13,"width":41,"height":5}},{"id":11,"definition":{"type":"timeseries","requests":[{"q":"sum:confluent.kafka.connect.worker.connector_count{*} by {host}","metadata":[{"expression":"sum:confluent.kafka.connect.worker.connector_count{*} by {host}","alias_name":"Postgres Rows Returned"}],"display_type":"bars","style":{"palette":"dog_classic","line_type":"solid","line_width":"normal"}}],"custom_links":[],"yaxis":{"label":"","scale":"linear","min":"auto","max":"auto","include_zero":true},"title":"Connectors Running","title_size":"16","title_align":"left","show_legend":false,"legend_size":"0"},"layout":{"x":43,"y":20,"width":41,"height":15}},{"id":12,"definition":{"type":"timeseries","requests":[{"q":"sum:confluent.kafka.connect.worker.connector_running_task_count{*} by {connector}","display_type":"bars","style":{"palette":"dog_classic","line_type":"solid","line_width":"normal"}}],"custom_links":[],"yaxis":{"label":"","scale":"linear","min":"auto","max":"auto","include_zero":true},"title":"Connector Tasks Running","title_size":"16","title_align":"left","show_legend":false,"legend_size":"0"},"layout":{"x":43,"y":35,"width":41,"height":15}},{"id":13,"definition":{"type":"timeseries","requests":[{"q":"sum:confluent.kafka.connect.worker_rebalance.completed_rebalances_total{*}","display_type":"bars","style":{"palette":"dog_classic","line_type":"solid","line_width":"normal"}}],"custom_links":[],"yaxis":{"label":"","scale":"linear","min":"auto","max":"auto","include_zero":true},"title":"Completed Rebalances","title_size":"16","title_align":"left","show_legend":false,"legend_size":"0"},"layout":{"x":43,"y":50,"width":41,"height":15}},{"id":14,"definition":{"type":"timeseries","requests":[{"q":"sum:confluent.kafka.server.topic.bytes_in_per_sec.rate{*} by {instance}","display_type":"line","style":{"palette":"dog_classic","line_type":"solid","line_width":"normal"}}],"custom_links":[],"yaxis":{"label":"","scale":"linear","min":"auto","max":"auto","include_zero":true},"title":"Bytes in per Second","title_size":"16","title_align":"left","show_legend":false,"legend_size":"0"},"layout":{"x":85,"y":8,"width":41,"height":15}},{"id":15,"definition":{"type":"note","content":"Brokers","background_color":"blue","font_size":"18","text_align":"center","show_tick":true,"tick_pos":"50%","tick_edge":"bottom"},"layout":{"x":85,"y":1,"width":41,"height":5}},{"id":16,"definition":{"type":"timeseries","requests":[{"q":"sum:confluent.kafka.server.topic.bytes_out_per_sec.rate{*}","display_type":"line","style":{"palette":"dog_classic","line_type":"solid","line_width":"normal"}}],"custom_links":[],"yaxis":{"label":"","scale":"linear","min":"auto","max":"auto","include_zero":true},"title":"Bytes Out per Second","title_size":"16","title_align":"left","show_legend":false,"legend_size":"0"},"layout":{"x":85,"y":23,"width":41,"height":15}},{"id":17,"definition":{"type":"timeseries","requests":[{"q":"sum:confluent.ksql.query_stats.num_active_queries{*}","display_type":"area","style":{"palette":"dog_classic","line_type":"solid","line_width":"normal"}}],"custom_links":[],"yaxis":{"label":"","scale":"linear","min":"auto","max":"auto","include_zero":true},"title":"KSQL Active Queries","title_size":"16","title_align":"left","show_legend":false,"legend_size":"0"},"layout":{"x":85,"y":46,"width":41,"height":15}},{"id":18,"definition":{"type":"note","content":"KSQLDB","background_color":"blue","font_size":"18","text_align":"center","show_tick":true,"tick_pos":"50%","tick_edge":"bottom"},"layout":{"x":85,"y":39,"width":41,"height":5}},{"id":19,"definition":{"type":"timeseries","requests":[{"q":"sum:confluent.ksql.query_stats.bytes_consumed_total{*}","display_type":"area","style":{"palette":"dog_classic","line_type":"solid","line_width":"normal"}}],"custom_links":[],"yaxis":{"label":"","scale":"linear","min":"auto","max":"auto","include_zero":true},"title":"Bytes Consumed","title_size":"16","title_align":"left","show_legend":false,"legend_size":"0"},"layout":{"x":85,"y":61,"width":41,"height":15}},{"id":20,"definition":{"type":"image","url":"/static/images/saas_logos/bot/elasticsearch.png","sizing":"center"},"layout":{"x":127,"y":1,"width":19,"height":11}},{"id":21,"definition":{"type":"check_status","title":"Elasticsearch Hosts","title_size":"16","title_align":"center","check":"elasticsearch.can_connect","grouping":"cluster","group":"docker_image:elasticsearch:7.6.2,server:192.168.192.4,image_name:elasticsearch,image_tag:7.6.2,port:9200,short_image:elasticsearch,host:i-0bccff6999c3c9509","group_by":[],"tags":["*"]},"layout":{"x":147,"y":1,"width":21,"height":11}},{"id":22,"definition":{"type":"timeseries","requests":[{"q":"sum:elasticsearch.http.current_open{*}","display_type":"bars","style":{"palette":"orange","line_type":"solid","line_width":"normal"}}],"custom_links":[],"yaxis":{"label":"","scale":"linear","min":"auto","max":"auto","include_zero":true},"title":"HTTP Connections","title_size":"16","title_align":"left","show_legend":false,"legend_size":"0"},"layout":{"x":127,"y":13,"width":41,"height":15}},{"id":23,"definition":{"type":"timeseries","requests":[{"q":"sum:elasticsearch.indexing.index.total{*}/sum:elasticsearch.indexing.index.time{*}","display_type":"line","style":{"palette":"orange","line_type":"solid","line_width":"normal"}}],"custom_links":[],"yaxis":{"label":"","scale":"linear","min":"auto","max":"auto","include_zero":true},"title":"Indexed Documents per Millisecond","title_size":"16","title_align":"left","show_legend":false,"legend_size":"0"},"layout":{"x":127,"y":43,"width":41,"height":15}},{"id":24,"definition":{"type":"timeseries","requests":[{"q":"sum:elasticsearch.indexing.index.total{*}","display_type":"bars","style":{"palette":"orange","line_type":"solid","line_width":"normal"}}],"custom_links":[],"yaxis":{"label":"","scale":"linear","min":"auto","max":"auto","include_zero":true},"title":"Documents Indexed","title_size":"16","title_align":"left","show_legend":false,"legend_size":"0"},"layout":{"x":127,"y":28,"width":41,"height":15}}],"template_variables":[],"layout_type":"free","is_read_only":false,"notify_list":[],"id":"7wc-ndh-s5x"}